cloudy/__init__.py
cloudy/random_sign.py
cloudycustoms-0.0.6.dist-info/LICENSE
cloudycustoms-0.0.6.dist-info/METADATA
cloudycustoms-0.0.6.dist-info/WHEEL
cloudycustoms-0.0.6.dist-info/top_level.txt
cloudycustoms-0.0.6.dist-info/RECORD
